{
  "openapi": "3.0.3",
  "info": {
    "title": "Oja Ewa Pro",
    "version": "1.0.0",
    "description": "Comprehensive e-commerce API for the Oja Ewa Pro platform",
    "contact": {
      "name": "API Support",
      "email": "support@ojaewa.com"
    }
  },
  "servers": [
    {
      "url": "http://localhost:8000/api",
      "description": "Local Development Server"
    },
    {
      "url": "https://test.ojaewa.com/api",
      "description": "Production Server"
    }
  ],
  "paths": {
    "/register": {
      "post": {
        "tags": ["User Auth"],
        "summary": "User registration",
        "parameters": [{"name": "Accept", "in": "header", "required": true, "schema": {"type": "string", "default": "application/json"}}],
        "responses": {"201": {}}
      }
    },
    "/login": {
      "post": {
        "tags": ["User Auth"],
        "summary": "User login",
        "parameters": [{"name": "Accept", "in": "header", "required": true, "schema": {"type": "string", "default": "application/json"}}],
        "responses": {"200": {}}
      }
    },
    "/password/forgot": {
      "post": {
        "tags": ["User Auth"],
        "summary": "Send reset link",
        "parameters": [{"name": "Accept", "in": "header", "required": true, "schema": {"type": "string", "default": "application/json"}}],
        "responses": {"200": {}}
      }
    },
    "/password/reset": {
      "post": {
        "tags": ["User Auth"],
        "summary": "Reset password",
        "parameters": [{"name": "Accept", "in": "header", "required": true, "schema": {"type": "string", "default": "application/json"}}],
        "responses": {"200": {}}
      }
    },
    "/oauth/google": {
      "post": {
        "tags": ["User Auth"],
        "summary": "Google OAuth login",
        "parameters": [{"name": "Accept", "in": "header", "required": true, "schema": {"type": "string", "default": "application/json"}}],
        "responses": {"200": {}}
      }
    },
    "/profile": {
      "get": {
        "tags": ["User Profile"],
        "summary": "Get user profile",
        "security": [{"bearerAuth": []}],
        "parameters": [{"name": "Accept", "in": "header", "required": true, "schema": {"type": "string", "default": "application/json"}}],
        "responses": {"200": {}}
      },
      "put": {
        "tags": ["User Profile"],
        "summary": "Update user profile",
        "security": [{"bearerAuth": []}],
        "parameters": [{"name": "Accept", "in": "header", "required": true, "schema": {"type": "string", "default": "application/json"}}],
        "responses": {"200": {}}
      }
    },
    "/password": {
      "put": {
        "tags": ["User Profile"],
        "summary": "Update password",
        "security": [{"bearerAuth": []}],
        "parameters": [{"name": "Accept", "in": "header", "required": true, "schema": {"type": "string", "default": "application/json"}}],
        "responses": {"200": {}}
      }
    },
    "/addresses": {
      "get": {
        "tags": ["User Profile"],
        "summary": "List addresses",
        "security": [{"bearerAuth": []}],
        "parameters": [{"name": "Accept", "in": "header", "required": true, "schema": {"type": "string", "default": "application/json"}}],
        "responses": {"200": {}}
      },
      "post": {
        "tags": ["User Profile"],
        "summary": "Create address",
        "security": [{"bearerAuth": []}],
        "parameters": [{"name": "Accept", "in": "header", "required": true, "schema": {"type": "string", "default": "application/json"}}],
        "responses": {"201": {}}
      }
    },
    "/addresses/{id}": {
      "get": {
        "tags": ["User Profile"],
        "summary": "Get address",
        "security": [{"bearerAuth": []}],
        "parameters": [
          {"name": "id", "in": "path", "required": true, "schema": {"type": "integer"}},
          {"name": "Accept", "in": "header", "required": true, "schema": {"type": "string", "default": "application/json"}}
        ],
        "responses": {"200": {}}
      },
      "put": {
        "tags": ["User Profile"],
        "summary": "Update address",
        "security": [{"bearerAuth": []}],
        "parameters": [
          {"name": "id", "in": "path", "required": true, "schema": {"type": "integer"}},
          {"name": "Accept", "in": "header", "required": true, "schema": {"type": "string", "default": "application/json"}}
        ],
        "responses": {"200": {}}
      },
      "delete": {
        "tags": ["User Profile"],
        "summary": "Delete address",
        "security": [{"bearerAuth": []}],
        "parameters": [
          {"name": "id", "in": "path", "required": true, "schema": {"type": "integer"}},
          {"name": "Accept", "in": "header", "required": true, "schema": {"type": "string", "default": "application/json"}}
        ],
        "responses": {"200": {}}
      }
    },
    "/products": {
      "get": {
        "tags": ["User Products"],
        "summary": "List products",
        "security": [{"bearerAuth": []}],
        "parameters": [{"name": "Accept", "in": "header", "required": true, "schema": {"type": "string", "default": "application/json"}}],
        "responses": {"200": {}}
      },
      "post": {
        "tags": ["User Products"],
        "summary": "Create product",
        "security": [{"bearerAuth": []}],
        "parameters": [{"name": "Accept", "in": "header", "required": true, "schema": {"type": "string", "default": "application/json"}}],
        "responses": {"201": {}}
      }
    },
    "/products/search": {
      "get": {
        "tags": ["User Products"],
        "summary": "Search products",
        "security": [{"bearerAuth": []}],
        "parameters": [{"name": "Accept", "in": "header", "required": true, "schema": {"type": "string", "default": "application/json"}}],
        "responses": {"200": {}}
      }
    },
    "/products/suggestions": {
      "get": {
        "tags": ["User Products"],
        "summary": "Get product suggestions",
        "security": [{"bearerAuth": []}],
        "parameters": [{"name": "Accept", "in": "header", "required": true, "schema": {"type": "string", "default": "application/json"}}],
        "responses": {"200": {}}
      }
    },
    "/products/{product}": {
      "get": {
        "tags": ["User Products"],
        "summary": "Get product",
        "security": [{"bearerAuth": []}],
        "parameters": [
          {"name": "product", "in": "path", "required": true, "schema": {"type": "integer"}},
          {"name": "Accept", "in": "header", "required": true, "schema": {"type": "string", "default": "application/json"}}
        ],
        "responses": {"200": {}}
      },
      "put": {
        "tags": ["User Products"],
        "summary": "Update product",
        "security": [{"bearerAuth": []}],
        "parameters": [
          {"name": "product", "in": "path", "required": true, "schema": {"type": "integer"}},
          {"name": "Accept", "in": "header", "required": true, "schema": {"type": "string", "default": "application/json"}}
        ],
        "responses": {"200": {}}
      },
      "delete": {
        "tags": ["User Products"],
        "summary": "Delete product",
        "security": [{"bearerAuth": []}],
        "parameters": [
          {"name": "product", "in": "path", "required": true, "schema": {"type": "integer"}},
          {"name": "Accept", "in": "header", "required": true, "schema": {"type": "string", "default": "application/json"}}
        ],
        "responses": {"200": {}}
      }
    },
    "/orders": {
      "get": {
        "tags": ["User Orders"],
        "summary": "List orders",
        "security": [{"bearerAuth": []}],
        "parameters": [{"name": "Accept", "in": "header", "required": true, "schema": {"type": "string", "default": "application/json"}}],
        "responses": {"200": {}}
      },
      "post": {
        "tags": ["User Orders"],
        "summary": "Create order",
        "security": [{"bearerAuth": []}],
        "parameters": [{"name": "Accept", "in": "header", "required": true, "schema": {"type": "string", "default": "application/json"}}],
        "responses": {"201": {}}
      }
    },
    "/orders/{order}": {
      "get": {
        "tags": ["User Orders"],
        "summary": "Get order",
        "security": [{"bearerAuth": []}],
        "parameters": [
          {"name": "order", "in": "path", "required": true, "schema": {"type": "integer"}},
          {"name": "Accept", "in": "header", "required": true, "schema": {"type": "string", "default": "application/json"}}
        ],
        "responses": {"200": {}}
      }
    },
    "/orders/{order}/tracking": {
      "get": {
        "tags": ["User Orders"],
        "summary": "Track order",
        "security": [{"bearerAuth": []}],
        "parameters": [
          {"name": "order", "in": "path", "required": true, "schema": {"type": "integer"}},
          {"name": "Accept", "in": "header", "required": true, "schema": {"type": "string", "default": "application/json"}}
        ],
        "responses": {"200": {}}
      }
    },
    "/reviews": {
      "post": {
        "tags": ["User Reviews"],
        "summary": "Create review",
        "security": [{"bearerAuth": []}],
        "parameters": [{"name": "Accept", "in": "header", "required": true, "schema": {"type": "string", "default": "application/json"}}],
        "responses": {"201": {}}
      }
    },
    "/reviews/{type}/{id}": {
      "get": {
        "tags": ["User Reviews"],
        "summary": "Get reviews by entity",
        "security": [{"bearerAuth": []}],
        "parameters": [
          {"name": "type", "in": "path", "required": true, "schema": {"type": "string"}},
          {"name": "id", "in": "path", "required": true, "schema": {"type": "integer"}},
          {"name": "Accept", "in": "header", "required": true, "schema": {"type": "string", "default": "application/json"}}
        ],
        "responses": {"200": {}}
      }
    },
    "/payment/link": {
      "post": {
        "tags": ["User Payment"],
        "summary": "Create order payment link",
        "security": [{"bearerAuth": []}],
        "parameters": [{"name": "Accept", "in": "header", "required": true, "schema": {"type": "string", "default": "application/json"}}],
        "responses": {"200": {}}
      }
    },
    "/payment/link/school": {
      "post": {
        "tags": ["User Payment"],
        "summary": "Create school payment link",
        "security": [{"bearerAuth": []}],
        "parameters": [{"name": "Accept", "in": "header", "required": true, "schema": {"type": "string", "default": "application/json"}}],
        "responses": {"200": {}}
      }
    },
    "/payment/verify": {
      "post": {
        "tags": ["User Payment"],
        "summary": "Verify payment",
        "security": [{"bearerAuth": []}],
        "parameters": [{"name": "Accept", "in": "header", "required": true, "schema": {"type": "string", "default": "application/json"}}],
        "responses": {"200": {}}
      }
    },
    "/wishlist": {
      "get": {
        "tags": ["User Wishlist"],
        "summary": "Get wishlist",
        "security": [{"bearerAuth": []}],
        "parameters": [{"name": "Accept", "in": "header", "required": true, "schema": {"type": "string", "default": "application/json"}}],
        "responses": {"200": {}}
      },
      "post": {
        "tags": ["User Wishlist"],
        "summary": "Add to wishlist",
        "security": [{"bearerAuth": []}],
        "parameters": [{"name": "Accept", "in": "header", "required": true, "schema": {"type": "string", "default": "application/json"}}],
        "responses": {"200": {}}
      },
      "delete": {
        "tags": ["User Wishlist"],
        "summary": "Remove from wishlist",
        "security": [{"bearerAuth": []}],
        "parameters": [{"name": "Accept", "in": "header", "required": true, "schema": {"type": "string", "default": "application/json"}}],
        "responses": {"200": {}}
      }
    },
    "/notifications": {
      "get": {
        "tags": ["User Notifications"],
        "summary": "List notifications",
        "security": [{"bearerAuth": []}],
        "parameters": [{"name": "Accept", "in": "header", "required": true, "schema": {"type": "string", "default": "application/json"}}],
        "responses": {"200": {}}
      }
    },
    "/notifications/unread-count": {
      "get": {
        "tags": ["User Notifications"],
        "summary": "Get unread count",
        "security": [{"bearerAuth": []}],
        "parameters": [{"name": "Accept", "in": "header", "required": true, "schema": {"type": "string", "default": "application/json"}}],
        "responses": {"200": {}}
      }
    },
    "/notifications/{id}/read": {
      "patch": {
        "tags": ["User Notifications"],
        "summary": "Mark as read",
        "security": [{"bearerAuth": []}],
        "parameters": [
          {"name": "id", "in": "path", "required": true, "schema": {"type": "integer"}},
          {"name": "Accept", "in": "header", "required": true, "schema": {"type": "string", "default": "application/json"}}
        ],
        "responses": {"200": {}}
      }
    },
    "/notifications/mark-all-read": {
      "patch": {
        "tags": ["User Notifications"],
        "summary": "Mark all as read",
        "security": [{"bearerAuth": []}],
        "parameters": [{"name": "Accept", "in": "header", "required": true, "schema": {"type": "string", "default": "application/json"}}],
        "responses": {"200": {}}
      }
    },
    "/notifications/filter": {
      "get": {
        "tags": ["User Notifications"],
        "summary": "Filter notifications",
        "security": [{"bearerAuth": []}],
        "parameters": [{"name": "Accept", "in": "header", "required": true, "schema": {"type": "string", "default": "application/json"}}],
        "responses": {"200": {}}
      }
    },
    "/notifications/{id}": {
      "delete": {
        "tags": ["User Notifications"],
        "summary": "Delete notification",
        "security": [{"bearerAuth": []}],
        "parameters": [
          {"name": "id", "in": "path", "required": true, "schema": {"type": "integer"}},
          {"name": "Accept", "in": "header", "required": true, "schema": {"type": "string", "default": "application/json"}}
        ],
        "responses": {"200": {}}
      }
    },
    "/notifications/preferences": {
      "get": {
        "tags": ["User Notifications"],
        "summary": "Get notification preferences",
        "security": [{"bearerAuth": []}],
        "parameters": [{"name": "Accept", "in": "header", "required": true, "schema": {"type": "string", "default": "application/json"}}],
        "responses": {"200": {}}
      },
      "put": {
        "tags": ["User Notifications"],
        "summary": "Update notification preferences",
        "security": [{"bearerAuth": []}],
        "parameters": [{"name": "Accept", "in": "header", "required": true, "schema": {"type": "string", "default": "application/json"}}],
        "responses": {"200": {}}
      }
    },
    "/blogs/favorites": {
      "get": {
        "tags": ["User Favorites"],
        "summary": "Get blog favorites",
        "security": [{"bearerAuth": []}],
        "parameters": [{"name": "Accept", "in": "header", "required": true, "schema": {"type": "string", "default": "application/json"}}],
        "responses": {"200": {}}
      },
      "post": {
        "tags": ["User Favorites"],
        "summary": "Add blog to favorites",
        "security": [{"bearerAuth": []}],
        "parameters": [{"name": "Accept", "in": "header", "required": true, "schema": {"type": "string", "default": "application/json"}}],
        "responses": {"200": {}}
      },
      "delete": {
        "tags": ["User Favorites"],
        "summary": "Remove blog from favorites",
        "security": [{"bearerAuth": []}],
        "parameters": [{"name": "Accept", "in": "header", "required": true, "schema": {"type": "string", "default": "application/json"}}],
        "responses": {"200": {}}
      }
    },
    "/seller/profile": {
      "get": {
        "tags": ["User Seller"],
        "summary": "Get seller profile",
        "security": [{"bearerAuth": []}],
        "parameters": [{"name": "Accept", "in": "header", "required": true, "schema": {"type": "string", "default": "application/json"}}],
        "responses": {"200": {}}
      },
      "post": {
        "tags": ["User Seller"],
        "summary": "Create seller profile",
        "security": [{"bearerAuth": []}],
        "parameters": [{"name": "Accept", "in": "header", "required": true, "schema": {"type": "string", "default": "application/json"}}],
        "responses": {"201": {}}
      },
      "put": {
        "tags": ["User Seller"],
        "summary": "Update seller profile",
        "security": [{"bearerAuth": []}],
        "parameters": [{"name": "Accept", "in": "header", "required": true, "schema": {"type": "string", "default": "application/json"}}],
        "responses": {"200": {}}
      },
      "delete": {
        "tags": ["User Seller"],
        "summary": "Delete seller profile",
        "security": [{"bearerAuth": []}],
        "parameters": [{"name": "Accept", "in": "header", "required": true, "schema": {"type": "string", "default": "application/json"}}],
        "responses": {"200": {}}
      }
    },
    "/seller/profile/upload": {
      "post": {
        "tags": ["User Seller"],
        "summary": "Upload seller documents",
        "security": [{"bearerAuth": []}],
        "parameters": [{"name": "Accept", "in": "header", "required": true, "schema": {"type": "string", "default": "application/json"}}],
        "responses": {"200": {}}
      }
    },
    "/business": {
      "get": {
        "tags": ["User Business"],
        "summary": "List business profiles",
        "security": [{"bearerAuth": []}],
        "parameters": [{"name": "Accept", "in": "header", "required": true, "schema": {"type": "string", "default": "application/json"}}],
        "responses": {"200": {}}
      },
      "post": {
        "tags": ["User Business"],
        "summary": "Create business profile",
        "security": [{"bearerAuth": []}],
        "parameters": [{"name": "Accept", "in": "header", "required": true, "schema": {"type": "string", "default": "application/json"}}],
        "responses": {"201": {}}
      }
    },
    "/business/{id}": {
      "get": {
        "tags": ["User Business"],
        "summary": "Get business profile",
        "security": [{"bearerAuth": []}],
        "parameters": [
          {"name": "id", "in": "path", "required": true, "schema": {"type": "integer"}},
          {"name": "Accept", "in": "header", "required": true, "schema": {"type": "string", "default": "application/json"}}
        ],
        "responses": {"200": {}}
      },
      "put": {
        "tags": ["User Business"],
        "summary": "Update business profile",
        "security": [{"bearerAuth": []}],
        "parameters": [
          {"name": "id", "in": "path", "required": true, "schema": {"type": "integer"}},
          {"name": "Accept", "in": "header", "required": true, "schema": {"type": "string", "default": "application/json"}}
        ],
        "responses": {"200": {}}
      },
      "delete": {
        "tags": ["User Business"],
        "summary": "Delete business profile",
        "security": [{"bearerAuth": []}],
        "parameters": [
          {"name": "id", "in": "path", "required": true, "schema": {"type": "integer"}},
          {"name": "Accept", "in": "header", "required": true, "schema": {"type": "string", "default": "application/json"}}
        ],
        "responses": {"200": {}}
      }
    },
    "/business/{id}/upload": {
      "post": {
        "tags": ["User Business"],
        "summary": "Upload business files",
        "security": [{"bearerAuth": []}],
        "parameters": [
          {"name": "id", "in": "path", "required": true, "schema": {"type": "integer"}},
          {"name": "Accept", "in": "header", "required": true, "schema": {"type": "string", "default": "application/json"}}
        ],
        "responses": {"200": {}}
      }
    },
    "/business/{id}/deactivate": {
      "patch": {
        "tags": ["User Business"],
        "summary": "Deactivate business profile",
        "security": [{"bearerAuth": []}],
        "parameters": [
          {"name": "id", "in": "path", "required": true, "schema": {"type": "integer"}},
          {"name": "Accept", "in": "header", "required": true, "schema": {"type": "string", "default": "application/json"}}
        ],
        "responses": {"200": {}}
      }
    },
    "/business/subscription": {
      "put": {
        "tags": ["User Business"],
        "summary": "Update subscription",
        "security": [{"bearerAuth": []}],
        "parameters": [{"name": "Accept", "in": "header", "required": true, "schema": {"type": "string", "default": "application/json"}}],
        "responses": {"200": {}}
      }
    },
    "/categories": {
      "get": {
        "tags": ["Public"],
        "summary": "Get categories",
        "parameters": [{"name": "Accept", "in": "header", "required": true, "schema": {"type": "string", "default": "application/json"}}],
        "responses": {"200": {}}
      }
    },
    "/categories/{id}/children": {
      "get": {
        "tags": ["Public"],
        "summary": "Get category children",
        "parameters": [
          {"name": "id", "in": "path", "required": true, "schema": {"type": "integer"}},
          {"name": "Accept", "in": "header", "required": true, "schema": {"type": "string", "default": "application/json"}}
        ],
        "responses": {"200": {}}
      }
    },
    "/blogs": {
      "get": {
        "tags": ["Public"],
        "summary": "List blogs",
        "parameters": [{"name": "Accept", "in": "header", "required": true, "schema": {"type": "string", "default": "application/json"}}],
        "responses": {"200": {}}
      }
    },
    "/blogs/{slug}": {
      "get": {
        "tags": ["Public"],
        "summary": "Get blog by slug",
        "parameters": [
          {"name": "slug", "in": "path", "required": true, "schema": {"type": "string"}},
          {"name": "Accept", "in": "header", "required": true, "schema": {"type": "string", "default": "application/json"}}
        ],
        "responses": {"200": {}}
      }
    },
    "/categories/{type}/{slug}/items": {
      "get": {
        "tags": ["Public"],
        "summary": "Get category items",
        "parameters": [
          {"name": "type", "in": "path", "required": true, "schema": {"type": "string"}},
          {"name": "slug", "in": "path", "required": true, "schema": {"type": "string"}},
          {"name": "Accept", "in": "header", "required": true, "schema": {"type": "string", "default": "application/json"}}
        ],
        "responses": {"200": {}}
      }
    },
    "/blogs/latest": {
      "get": {
        "tags": ["Public"],
        "summary": "Get latest blogs",
        "parameters": [{"name": "Accept", "in": "header", "required": true, "schema": {"type": "string", "default": "application/json"}}],
        "responses": {"200": {}}
      }
    },
    "/blogs/search": {
      "get": {
        "tags": ["Public"],
        "summary": "Search blogs",
        "parameters": [{"name": "Accept", "in": "header", "required": true, "schema": {"type": "string", "default": "application/json"}}],
        "responses": {"200": {}}
      }
    },
    "/faqs": {
      "get": {
        "tags": ["Public"],
        "summary": "List FAQs",
        "parameters": [{"name": "Accept", "in": "header", "required": true, "schema": {"type": "string", "default": "application/json"}}],
        "responses": {"200": {}}
      }
    },
    "/faqs/categories": {
      "get": {
        "tags": ["Public"],
        "summary": "Get FAQ categories",
        "parameters": [{"name": "Accept", "in": "header", "required": true, "schema": {"type": "string", "default": "application/json"}}],
        "responses": {"200": {}}
      }
    },
    "/faqs/search": {
      "get": {
        "tags": ["Public"],
        "summary": "Search FAQs",
        "parameters": [{"name": "Accept", "in": "header", "required": true, "schema": {"type": "string", "default": "application/json"}}],
        "responses": {"200": {}}
      }
    },
    "/faqs/{id}": {
      "get": {
        "tags": ["Public"],
        "summary": "Get FAQ by ID",
        "parameters": [
          {"name": "id", "in": "path", "required": true, "schema": {"type": "integer"}},
          {"name": "Accept", "in": "header", "required": true, "schema": {"type": "string", "default": "application/json"}}
        ],
        "responses": {"200": {}}
      }
    },
    "/connect": {
      "get": {
        "tags": ["Public"],
        "summary": "Get connect info",
        "parameters": [{"name": "Accept", "in": "header", "required": true, "schema": {"type": "string", "default": "application/json"}}],
        "responses": {"200": {}}
      }
    },
    "/connect/social": {
      "get": {
        "tags": ["Public"],
        "summary": "Get social links",
        "parameters": [{"name": "Accept", "in": "header", "required": true, "schema": {"type": "string", "default": "application/json"}}],
        "responses": {"200": {}}
      }
    },
    "/connect/contact": {
      "get": {
        "tags": ["Public"],
        "summary": "Get contact info",
        "parameters": [{"name": "Accept", "in": "header", "required": true, "schema": {"type": "string", "default": "application/json"}}],
        "responses": {"200": {}}
      }
    },
    "/connect/app-links": {
      "get": {
        "tags": ["Public"],
        "summary": "Get app links",
        "parameters": [{"name": "Accept", "in": "header", "required": true, "schema": {"type": "string", "default": "application/json"}}],
        "responses": {"200": {}}
      }
    },
    "/school-registrations": {
      "post": {
        "tags": ["Public"],
        "summary": "Register school",
        "parameters": [{"name": "Accept", "in": "header", "required": true, "schema": {"type": "string", "default": "application/json"}}],
        "responses": {"201": {}}
      }
    },
    "/webhook/paystack": {
      "post": {
        "tags": ["Public"],
        "summary": "Paystack order webhook",
        "parameters": [{"name": "Accept", "in": "header", "required": true, "schema": {"type": "string", "default": "application/json"}}],
        "responses": {"200": {}}
      }
    },
    "/webhook/paystack/school": {
      "post": {
        "tags": ["Public"],
        "summary": "Paystack school webhook",
        "parameters": [{"name": "Accept", "in": "header", "required": true, "schema": {"type": "string", "default": "application/json"}}],
        "responses": {"200": {}}
      }
    },
    "/admin/login": {
      "post": {
        "tags": ["Admin Auth"],
        "summary": "Admin login",
        "parameters": [{"name": "Accept", "in": "header", "required": true, "schema": {"type": "string", "default": "application/json"}}],
        "responses": {"200": {}}
      }
    },
    "/admin/create": {
      "post": {
        "tags": ["Admin Auth"],
        "summary": "Create admin",
        "parameters": [{"name": "Accept", "in": "header", "required": true, "schema": {"type": "string", "default": "application/json"}}],
        "responses": {"201": {}}
      }
    },
    "/admin/profile": {
      "get": {
        "tags": ["Admin Auth"],
        "summary": "Get admin profile",
        "security": [{"bearerAuth": []}],
        "parameters": [{"name": "Accept", "in": "header", "required": true, "schema": {"type": "string", "default": "application/json"}}],
        "responses": {"200": {}}
      }
    },
    "/admin/logout": {
      "post": {
        "tags": ["Admin Auth"],
        "summary": "Admin logout",
        "security": [{"bearerAuth": []}],
        "parameters": [{"name": "Accept", "in": "header", "required": true, "schema": {"type": "string", "default": "application/json"}}],
        "responses": {"200": {}}
      }
    },
    "/admin/dashboard/overview": {
      "get": {
        "tags": ["Admin Dashboard"],
        "summary": "Get dashboard overview",
        "security": [{"bearerAuth": []}],
        "parameters": [{"name": "Accept", "in": "header", "required": true, "schema": {"type": "string", "default": "application/json"}}],
        "responses": {"200": {}}
      }
    },
    "/admin/users": {
      "get": {
        "tags": ["Admin Users"],
        "summary": "List users",
        "security": [{"bearerAuth": []}],
        "parameters": [{"name": "Accept", "in": "header", "required": true, "schema": {"type": "string", "default": "application/json"}}],
        "responses": {"200": {}}
      }
    },
    "/admin/market/sellers": {
      "get": {
        "tags": ["Admin Market"],
        "summary": "List sellers",
        "security": [{"bearerAuth": []}],
        "parameters": [{"name": "Accept", "in": "header", "required": true, "schema": {"type": "string", "default": "application/json"}}],
        "responses": {"200": {}}
      }
    },
    "/admin/pending/sellers": {
      "get": {
        "tags": ["Admin Market"],
        "summary": "List pending sellers",
        "security": [{"bearerAuth": []}],
        "parameters": [{"name": "Accept", "in": "header", "required": true, "schema": {"type": "string", "default": "application/json"}}],
        "responses": {"200": {}}
      }
    },
    "/admin/sellers/{id}": {
      "get": {
        "tags": ["Admin Market"],
        "summary": "Get seller details",
        "security": [{"bearerAuth": []}],
        "parameters": [
          {"name": "id", "in": "path", "required": true, "schema": {"type": "integer"}},
          {"name": "Accept", "in": "header", "required": true, "schema": {"type": "string", "default": "application/json"}}
        ],
        "responses": {"200": {}}
      }
    },
    "/admin/seller/{id}/approve": {
      "patch": {
        "tags": ["Admin Market"],
        "summary": "Approve seller",
        "security": [{"bearerAuth": []}],
        "parameters": [
          {"name": "id", "in": "path", "required": true, "schema": {"type": "integer"}},
          {"name": "Accept", "in": "header", "required": true, "schema": {"type": "string", "default": "application/json"}}
        ],
        "responses": {"200": {}}
      }
    },
    "/admin/market/seller/{id}/status": {
      "patch": {
        "tags": ["Admin Market"],
        "summary": "Update seller status",
        "security": [{"bearerAuth": []}],
        "parameters": [
          {"name": "id", "in": "path", "required": true, "schema": {"type": "integer"}},
          {"name": "Accept", "in": "header", "required": true, "schema": {"type": "string", "default": "application/json"}}
        ],
        "responses": {"200": {}}
      }
    },
    "/admin/market/products": {
      "get": {
        "tags": ["Admin Market"],
        "summary": "List products",
        "security": [{"bearerAuth": []}],
        "parameters": [{"name": "Accept", "in": "header", "required": true, "schema": {"type": "string", "default": "application/json"}}],
        "responses": {"200": {}}
      }
    },
    "/admin/pending/products": {
      "get": {
        "tags": ["Admin Market"],
        "summary": "List pending products",
        "security": [{"bearerAuth": []}],
        "parameters": [{"name": "Accept", "in": "header", "required": true, "schema": {"type": "string", "default": "application/json"}}],
        "responses": {"200": {}}
      }
    },
    "/admin/products/{id}": {
      "get": {
        "tags": ["Admin Market"],
        "summary": "Get product details",
        "security": [{"bearerAuth": []}],
        "parameters": [
          {"name": "id", "in": "path", "required": true, "schema": {"type": "integer"}},
          {"name": "Accept", "in": "header", "required": true, "schema": {"type": "string", "default": "application/json"}}
        ],
        "responses": {"200": {}}
      }
    },
    "/admin/product/{id}/approve": {
      "patch": {
        "tags": ["Admin Market"],
        "summary": "Approve product",
        "security": [{"bearerAuth": []}],
        "parameters": [
          {"name": "id", "in": "path", "required": true, "schema": {"type": "integer"}},
          {"name": "Accept", "in": "header", "required": true, "schema": {"type": "string", "default": "application/json"}}
        ],
        "responses": {"200": {}}
      }
    },
    "/admin/market/product/{id}/status": {
      "patch": {
        "tags": ["Admin Market"],
        "summary": "Update product status",
        "security": [{"bearerAuth": []}],
        "parameters": [
          {"name": "id", "in": "path", "required": true, "schema": {"type": "integer"}},
          {"name": "Accept", "in": "header", "required": true, "schema": {"type": "string", "default": "application/json"}}
        ],
        "responses": {"200": {}}
      }
    },
    "/admin/orders": {
      "get": {
        "tags": ["Admin Market"],
        "summary": "List orders",
        "security": [{"bearerAuth": []}],
        "parameters": [{"name": "Accept", "in": "header", "required": true, "schema": {"type": "string", "default": "application/json"}}],
        "responses": {"200": {}}
      }
    },
    "/admin/order/{id}": {
      "get": {
        "tags": ["Admin Market"],
        "summary": "Get order",
        "security": [{"bearerAuth": []}],
        "parameters": [
          {"name": "id", "in": "path", "required": true, "schema": {"type": "integer"}},
          {"name": "Accept", "in": "header", "required": true, "schema": {"type": "string", "default": "application/json"}}
        ],
        "responses": {"200": {}}
      }
    },
    "/admin/order/{id}/status": {
      "patch": {
        "tags": ["Admin Market"],
        "summary": "Update order status",
        "security": [{"bearerAuth": []}],
        "parameters": [
          {"name": "id", "in": "path", "required": true, "schema": {"type": "integer"}},
          {"name": "Accept", "in": "header", "required": true, "schema": {"type": "string", "default": "application/json"}}
        ],
        "responses": {"200": {}}
      }
    },
    "/admin/business/{category}": {
      "get": {
        "tags": ["Admin Business"],
        "summary": "List business profiles by category",
        "security": [{"bearerAuth": []}],
        "parameters": [
          {"name": "category", "in": "path", "required": true, "schema": {"type": "string"}},
          {"name": "Accept", "in": "header", "required": true, "schema": {"type": "string", "default": "application/json"}}
        ],
        "responses": {"200": {}}
      }
    },
    "/admin/business/{category}/{id}": {
      "get": {
        "tags": ["Admin Business"],
        "summary": "Get business profile",
        "security": [{"bearerAuth": []}],
        "parameters": [
          {"name": "category", "in": "path", "required": true, "schema": {"type": "string"}},
          {"name": "id", "in": "path", "required": true, "schema": {"type": "integer"}},
          {"name": "Accept", "in": "header", "required": true, "schema": {"type": "string", "default": "application/json"}}
        ],
        "responses": {"200": {}}
      }
    },
    "/admin/business/{category}/{id}/status": {
      "patch": {
        "tags": ["Admin Business"],
        "summary": "Update business status",
        "security": [{"bearerAuth": []}],
        "parameters": [
          {"name": "category", "in": "path", "required": true, "schema": {"type": "string"}},
          {"name": "id", "in": "path", "required": true, "schema": {"type": "integer"}},
          {"name": "Accept", "in": "header", "required": true, "schema": {"type": "string", "default": "application/json"}}
        ],
        "responses": {"200": {}}
      }
    },
    "/admin/blogs": {
      "get": {
        "tags": ["Admin Content"],
        "summary": "List blogs",
        "security": [{"bearerAuth": []}],
        "parameters": [{"name": "Accept", "in": "header", "required": true, "schema": {"type": "string", "default": "application/json"}}],
        "responses": {"200": {}}
      },
      "post": {
        "tags": ["Admin Content"],
        "summary": "Create blog",
        "security": [{"bearerAuth": []}],
        "parameters": [{"name": "Accept", "in": "header", "required": true, "schema": {"type": "string", "default": "application/json"}}],
        "responses": {"201": {}}
      }
    },
    "/admin/blogs/{id}": {
      "get": {
        "tags": ["Admin Content"],
        "summary": "Get blog",
        "security": [{"bearerAuth": []}],
        "parameters": [
          {"name": "id", "in": "path", "required": true, "schema": {"type": "integer"}},
          {"name": "Accept", "in": "header", "required": true, "schema": {"type": "string", "default": "application/json"}}
        ],
        "responses": {"200": {}}
      },
      "put": {
        "tags": ["Admin Content"],
        "summary": "Update blog",
        "security": [{"bearerAuth": []}],
        "parameters": [
          {"name": "id", "in": "path", "required": true, "schema": {"type": "integer"}},
          {"name": "Accept", "in": "header", "required": true, "schema": {"type": "string", "default": "application/json"}}
        ],
        "responses": {"200": {}}
      },
      "delete": {
        "tags": ["Admin Content"],
        "summary": "Delete blog",
        "security": [{"bearerAuth": []}],
        "parameters": [
          {"name": "id", "in": "path", "required": true, "schema": {"type": "integer"}},
          {"name": "Accept", "in": "header", "required": true, "schema": {"type": "string", "default": "application/json"}}
        ],
        "responses": {"200": {}}
      }
    },
    "/admin/blogs/{id}/toggle-publish": {
      "patch": {
        "tags": ["Admin Content"],
        "summary": "Toggle blog publish status",
        "security": [{"bearerAuth": []}],
        "parameters": [
          {"name": "id", "in": "path", "required": true, "schema": {"type": "integer"}},
          {"name": "Accept", "in": "header", "required": true, "schema": {"type": "string", "default": "application/json"}}
        ],
        "responses": {"200": {}}
      }
    },
    "/admin/adverts": {
      "get": {
        "tags": ["Admin Content"],
        "summary": "List adverts",
        "security": [{"bearerAuth": []}],
        "parameters": [{"name": "Accept", "in": "header", "required": true, "schema": {"type": "string", "default": "application/json"}}],
        "responses": {"200": {}}
      },
      "post": {
        "tags": ["Admin Content"],
        "summary": "Create advert",
        "security": [{"bearerAuth": []}],
        "parameters": [{"name": "Accept", "in": "header", "required": true, "schema": {"type": "string", "default": "application/json"}}],
        "responses": {"201": {}}
      }
    },
    "/admin/adverts/{advert}": {
      "put": {
        "tags": ["Admin Content"],
        "summary": "Update advert",
        "security": [{"bearerAuth": []}],
        "parameters": [
          {"name": "advert", "in": "path", "required": true, "schema": {"type": "integer"}},
          {"name": "Accept", "in": "header", "required": true, "schema": {"type": "string", "default": "application/json"}}
        ],
        "responses": {"200": {}}
      },
      "delete": {
        "tags": ["Admin Content"],
        "summary": "Delete advert",
        "security": [{"bearerAuth": []}],
        "parameters": [
          {"name": "advert", "in": "path", "required": true, "schema": {"type": "integer"}},
          {"name": "Accept", "in": "header", "required": true, "schema": {"type": "string", "default": "application/json"}}
        ],
        "responses": {"200": {}}
      }
    },
    "/admin/school-registrations": {
      "get": {
        "tags": ["Admin School"],
        "summary": "List school registrations",
        "security": [{"bearerAuth": []}],
        "parameters": [{"name": "Accept", "in": "header", "required": true, "schema": {"type": "string", "default": "application/json"}}],
        "responses": {"200": {}}
      }
    },
    "/admin/school-registrations/{schoolRegistration}": {
      "get": {
        "tags": ["Admin School"],
        "summary": "Get school registration",
        "security": [{"bearerAuth": []}],
        "parameters": [
          {"name": "schoolRegistration", "in": "path", "required": true, "schema": {"type": "integer"}},
          {"name": "Accept", "in": "header", "required": true, "schema": {"type": "string", "default": "application/json"}}
        ],
        "responses": {"200": {}}
      },
      "put": {
        "tags": ["Admin School"],
        "summary": "Update school registration",
        "security": [{"bearerAuth": []}],
        "parameters": [
          {"name": "schoolRegistration", "in": "path", "required": true, "schema": {"type": "integer"}},
          {"name": "Accept", "in": "header", "required": true, "schema": {"type": "string", "default": "application/json"}}
        ],
        "responses": {"200": {}}
      },
      "delete": {
        "tags": ["Admin School"],
        "summary": "Delete school registration",
        "security": [{"bearerAuth": []}],
        "parameters": [
          {"name": "schoolRegistration", "in": "path", "required": true, "schema": {"type": "integer"}},
          {"name": "Accept", "in": "header", "required": true, "schema": {"type": "string", "default": "application/json"}}
        ],
        "responses": {"200": {}}
      }
    },
    "/admin/sustainability": {
      "get": {
        "tags": ["Admin Sustainability"],
        "summary": "List sustainability initiatives",
        "security": [{"bearerAuth": []}],
        "parameters": [{"name": "Accept", "in": "header", "required": true, "schema": {"type": "string", "default": "application/json"}}],
        "responses": {"200": {}}
      },
      "post": {
        "tags": ["Admin Sustainability"],
        "summary": "Create sustainability initiative",
        "security": [{"bearerAuth": []}],
        "parameters": [{"name": "Accept", "in": "header", "required": true, "schema": {"type": "string", "default": "application/json"}}],
        "responses": {"201": {}}
      }
    },
    "/admin/sustainability/{sustainabilityInitiative}": {
      "put": {
        "tags": ["Admin Sustainability"],
        "summary": "Update sustainability initiative",
        "security": [{"bearerAuth": []}],
        "parameters": [
          {"name": "sustainabilityInitiative", "in": "path", "required": true, "schema": {"type": "integer"}},
          {"name": "Accept", "in": "header", "required": true, "schema": {"type": "string", "default": "application/json"}}
        ],
        "responses": {"200": {}}
      },
      "delete": {
        "tags": ["Admin Sustainability"],
        "summary": "Delete sustainability initiative",
        "security": [{"bearerAuth": []}],
        "parameters": [
          {"name": "sustainabilityInitiative", "in": "path", "required": true, "schema": {"type": "integer"}},
          {"name": "Accept", "in": "header", "required": true, "schema": {"type": "string", "default": "application/json"}}
        ],
        "responses": {"200": {}}
      }
    },
    "/admin/notifications/send": {
      "post": {
        "tags": ["Admin Settings"],
        "summary": "Send notification",
        "security": [{"bearerAuth": []}],
        "parameters": [{"name": "Accept", "in": "header", "required": true, "schema": {"type": "string", "default": "application/json"}}],
        "responses": {"200": {}}
      }
    },
    "/admin/settings": {
      "get": {
        "tags": ["Admin Settings"],
        "summary": "Get settings",
        "security": [{"bearerAuth": []}],
        "parameters": [{"name": "Accept", "in": "header", "required": true, "schema": {"type": "string", "default": "application/json"}}],
        "responses": {"200": {}}
      },
      "put": {
        "tags": ["Admin Settings"],
        "summary": "Update settings",
        "security": [{"bearerAuth": []}],
        "parameters": [{"name": "Accept", "in": "header", "required": true, "schema": {"type": "string", "default": "application/json"}}],
        "responses": {"200": {}}
      }
    }
  },
  "tags": [
    {"name": "User Auth", "description": "User authentication"},
    {"name": "User Profile", "description": "User profile management"},
    {"name": "User Products", "description": "Product operations"},
    {"name": "User Orders", "description": "Order management"},
    {"name": "User Reviews", "description": "Review system"},
    {"name": "User Business", "description": "Business profiles"},
    {"name": "User Seller", "description": "Seller profiles"},
    {"name": "User Notifications", "description": "Notifications"},
    {"name": "User Wishlist", "description": "Wishlist operations"},
    {"name": "User Payment", "description": "Payment operations"},
    {"name": "User Favorites", "description": "Blog favorites"},
    {"name": "Admin Auth", "description": "Admin authentication"},
    {"name": "Admin Dashboard", "description": "Admin dashboard"},
    {"name": "Admin Users", "description": "Admin user management"},
    {"name": "Admin Market", "description": "Admin market management"},
    {"name": "Admin Business", "description": "Admin business management"},
    {"name": "Admin Content", "description": "Admin content management"},
    {"name": "Admin School", "description": "Admin school registrations"},
    {"name": "Admin Sustainability", "description": "Admin sustainability initiatives"},
    {"name": "Admin Settings", "description": "Admin settings and notifications"},
    {"name": "Public", "description": "Public endpoints"}
  ],
  "components": {
    "securitySchemes": {
      "bearerAuth": {
        "type": "http",
        "scheme": "bearer",
        "bearerFormat": "JWT"
      }
    }
  }
}